py_carouselgreedy/__init__.py
py_carouselgreedy/py_carouselgreedy.py
py_carouselgreedy-0.0.6.dist-info/licenses/LICENSE
py_carouselgreedy-0.0.6.dist-info/METADATA
py_carouselgreedy-0.0.6.dist-info/WHEEL
py_carouselgreedy-0.0.6.dist-info/top_level.txt
py_carouselgreedy-0.0.6.dist-info/RECORD
