Metadata-Version: 2.4
Name: py_carouselgreedy
Version: 0.0.6
Summary: A Python library implementing the Carousel Greedy Algorithm.
Author-email: Carmine Cerrone <carmine.cerrone@unige.it>, Raffaele Dragone <raffaele.dragone@edu.unige.it>
License: BSD-3-Clause
Project-URL: Homepage, https://pypi.org/project/py_carouselgreedy/
Project-URL: Repository, https://github.com/CarmineCerrone/py_carouselgreedy
Requires-Python: >=3.7
License-File: LICENSE
Dynamic: license-file
